vix/VixBackend.py
vix/VixError.py
vix/VixHandle.py
vix/VixHost.py
vix/VixJob.py
vix/VixSnapshot.py
vix/VixVM.py
vix/__init__.py
vix/compat.py
vix-1.0.8.dist-info/LICENSE.txt
vix-1.0.8.dist-info/METADATA
vix-1.0.8.dist-info/WHEEL
vix-1.0.8.dist-info/top_level.txt
vix-1.0.8.dist-info/RECORD
