Metadata-Version: 2.1
Name: vix
Version: 1.0.8
Summary: VMware VIX binding for Python (unofficial)
Home-page: https://github.com/naim94a/vix
Author: Naim A.
Author-email: naim94a@gmail.com
License: GPLv3
Project-URL: Documentation, https://naim94a.github.io/vix
Project-URL: Source, https://github.com/naim94a/vix
Project-URL: Bugs & Features, https://github.com/naim94a/vix/issues
Keywords: vmware python api vix
Platform: UNKNOWN
Classifier: Development Status :: 5 - Production/Stable
Classifier: Intended Audience :: Developers
Classifier: Intended Audience :: Information Technology
Classifier: Intended Audience :: System Administrators
Classifier: License :: OSI Approved :: GNU General Public License v3 (GPLv3)
Classifier: Natural Language :: English
Classifier: Operating System :: Microsoft :: Windows
Classifier: Operating System :: POSIX :: Linux
Classifier: Programming Language :: Python :: 2
Classifier: Programming Language :: Python :: 3
Classifier: Programming Language :: Python :: Implementation :: CPython
Classifier: Programming Language :: Python :: Implementation :: PyPy
Classifier: Topic :: System :: Systems Administration
License-File: LICENSE.txt
Requires-Dist: cffi (>=1.15)
Requires-Dist: six
